pyrwrapper/__init__.py
pyrwrapper/_nbdev.py
pyrwrapper/cmdl.py
pyrwrapper/colors.py
pyrwrapper/formats.py
pyrwrapper/pipelines.py
pyrwrapper/utils.py
pyrwrapper/rscripts/__init__.py
pyrwrapper/rscripts/check.py
pyrwrapper/rscripts/affy/__init__.py
pyrwrapper/rscripts/affy/annotate.py
pyrwrapper/rscripts/debulk/__init__.py
pyrwrapper/rscripts/debulk/music.py
pyrwrapper/rscripts/formatstrans/__init__.py
pyrwrapper/rscripts/formatstrans/rds.py
pyrwrapper/rscripts/plots/__init__.py
pyrwrapper/rscripts/plots/complexheatmap.py
pyrwrapper/rscripts/plots/venn.py
pyrwrapper-0.0.1rc4.dist-info/LICENSE
pyrwrapper-0.0.1rc4.dist-info/METADATA
pyrwrapper-0.0.1rc4.dist-info/WHEEL
pyrwrapper-0.0.1rc4.dist-info/entry_points.txt
pyrwrapper-0.0.1rc4.dist-info/top_level.txt
pyrwrapper-0.0.1rc4.dist-info/RECORD
