Metadata-Version: 2.1
Name: pyrwrapper
Version: 0.0.1rc4
Summary: r scripts wrapper
Home-page: https://github.com/btrspg/pyrwrapper/tree/master/
Author: Yuelong CHEN
Author-email: yuelong.chen.btr@gmail.com
License: Apache Software License 2.0
Keywords: R Python Wrapper
Platform: UNKNOWN
Classifier: Development Status :: 2 - Pre-Alpha
Classifier: Intended Audience :: Developers
Classifier: License :: OSI Approved :: Apache Software License
Classifier: Natural Language :: English
Classifier: Programming Language :: Python :: 3.6
Classifier: Programming Language :: Python :: 3.7
Classifier: Programming Language :: Python :: 3.8
Requires-Python: >=3.6
Requires-Dist: defopt
Requires-Dist: matplotlib
Requires-Dist: pandas
